Metadata-Version: 2.4
Name: swe-rex-preview
Version: 1.2.2
Summary: Sandboxed code execution for AI agents, locally or on the cloud.
Author-email: Kilian Lieret <kilian.lieret@posteo.de>, "Carlos E. Jimenez" <carlosej@princeton.edu>, John Yang <byjohnyang@gmail.com>
Project-URL: Homepage, https://swe-rex.com
Project-URL: Bug Reports, http://github.com/SWE-agent/SWE-rex/issues
Project-URL: Documentation, https://swe-rex.com/latest/
Project-URL: Source, http://github.com/SWE-agent/SWE-rex
Keywords: nlp,agents,code
Classifier: Operating System :: OS Independent
Classifier: Intended Audience :: Developers
Classifier: License :: OSI Approved :: MIT License
Classifier: Programming Language :: Python :: 3.11
Classifier: Programming Language :: Python :: 3 :: Only
Requires-Python: >=3.10
License-File: LICENSE.txt
Requires-Dist: fastapi
Requires-Dist: uvicorn
Requires-Dist: requests
Requires-Dist: pydantic>=2
Requires-Dist: pexpect
Requires-Dist: bashlex
Requires-Dist: python-multipart
Requires-Dist: rich
Provides-Extra: dev
Requires-Dist: mike; extra == "dev"
Requires-Dist: mkdocs-material; extra == "dev"
Requires-Dist: mkdocs-glightbox; extra == "dev"
Requires-Dist: mkdocs-include-markdown-plugin; extra == "dev"
Requires-Dist: mkdocstrings[python]>=0.18; extra == "dev"
Requires-Dist: pytest; extra == "dev"
Requires-Dist: pytest-cov; extra == "dev"
Requires-Dist: pre-commit; extra == "dev"
Requires-Dist: pytest-asyncio; extra == "dev"
Requires-Dist: griffe-pydantic; extra == "dev"
Requires-Dist: swe-rex[modal]; extra == "dev"
Requires-Dist: swe-rex[fargate]; extra == "dev"
Provides-Extra: modal
Requires-Dist: modal; extra == "modal"
Requires-Dist: boto3; extra == "modal"
Provides-Extra: fargate
Requires-Dist: boto3; extra == "fargate"
Dynamic: license-file
